

{"intents": [
    {"tag": "automated_cars",
     "patterns": ["automated car", "automated vehicle", "self-driving car", "self-driving vehicle", "autonomous vehicle", "autonomous transportation system"],
     "response_list": ["automated_systems", "automated_vehicle_system","common_nfr","sensitive_nfr"]},

    {"tag": "automated_systems",
        "patterns": ["Automation",
        "Artificial intelligence (AI)",
        "Machine learning",
        "Predictive modeling",
        "Decision-making",
        "Self-learning",
        "Feedback loop",
        "Streamlining",
        "Real-time monitoring"],
        "responses": ["automated_systems","common_nfr"]
    },
    {"tag": "educational_system",
        "patterns": ["Learning",
        "Education",
        "E-Learning",
        "Student",
        "Personalized learning",
        "Student engagement",
        "Virtual classroom",
        "Tutoring",
        "Online courses",
        "Adaptive learning",
        "Digital literacy",
        "Academic performance",
        "Study aids",
        "Student-centered."],
        "responses": ["common_nfr","interactive_website","work_or_school_website","educational_website","transaction_system","online_system"]
    },
    {"tag": "ecommerce_system",
        "patterns": ["Shopping cart",
        "Online store",
        "E-commerce platform",
        "Inventory management",
        "Product catalog",
        "Order tracking",
        "Shipping and delivery",
        "Discounts and promotions",
        "Cross-selling and upselling",
        "Return and refund management",
        "Wish list",
        "Product search"],
        "responses": ["common_nfr","interactive_website","transaction_system","online_system"]
    },
    {"tag": "social_system",
        "patterns": ["Social network",
        "Profile",
        "Newsfeed",
        "Followers",
        "Friends",
        "Likes and reactions",
        "Sharing",
        "Direct messaging",
        "User-generated content",
        "Groups and communities",
        "Live streaming",
        "Audio and video calls"],
        "responses": ["common_nfr","interactive_website","online_system","social_network"]
    },
    {"tag": "transaction_system",
        "patterns": ["Payment gateway",
        "Banking",
        "Finance",
        "Transactions",
        "Payment processing",
        "Refunds and cancellations",
        "Billing and invoicing",
        "Accounts receivable",
        "Accounts payable",
        "Currency exchange",
        "Digital wallets",
        "Audit trail"],
        "responses": ["common_nfr","sensitive_nfr","transaction_system"]
    },
    {"tag": "streaming_system",
        "patterns": ["Video streaming",
        "Multimedia streaming",
        "Audiobook",
        "Audio streaming",
        "On-demand content",
        "Content library",
        "Playlist creation",
        "Content categorization",
        "Video player"],
        "responses": ["common_nfr","transaction_system", "interactive_website","online_system","streaming_service"]
    },
    {"tag": "file_storage_system",
        "patterns": ["Cloud storage",
        "Local storage",
        "File sharing",
        "Backup and recovery",
        "File indexing",
        "Compression",
        "De-duplication",
        "Collaboration"],
        "responses": ["common_nfr","transaction_system", "interactive_website","online_system","file_storage_system"]
    },
    {"tag": "web_based_system",
        "patterns": ["web based", "online", "interactive"],
        "responses": ["interactive_website"]
    },
    {"tag": "unknown",
        "patterns": [""],
        "responses": ["common_nfr"]
    }
]
}